{
    "atlas": {
        "type": "msdf",
        "distanceRange": 2,
        "distanceRangeMiddle": 0,
        "size": 32.625,
        "width": 212,
        "height": 212,
        "yOrigin": "bottom"
    },
    "metrics": {
        "emSize": 1,
        "lineHeight": 1.36181640625,
        "ascender": 1.06884765625,
        "descender": -0.29296875,
        "underlineY": -0.10009765625,
        "underlineThickness": 0.0498046875
    },
    "glyphs": [
        {
            "unicode": 32,
            "advance": 0.259765625
        },
        {
            "unicode": 33,
            "advance": 0.240234375,
            "planeBounds": {
                "left": 0.043000553759578564,
                "bottom": -0.045977011494252873,
                "right": 0.19625725874042146,
                "top": 0.75095785440613028
            },
            "atlasBounds": {
                "left": 0.5,
                "bottom": 90.5,
                "right": 5.5,
                "top": 116.5
            }
        },
        {
            "unicode": 34,
            "advance": 0.35302734375,
            "planeBounds": {
                "left": 0.023256966894157065,
                "bottom": 0.41379310344827586,
                "right": 0.32977037685584287,
                "top": 0.75095785440613017
            },
            "atlasBounds": {
                "left": 0.5,
                "bottom": 2.5,
                "right": 10.5,
                "top": 13.5
            }
        },
        {
            "unicode": 35,
            "advance": 0.64599609375,
            "planeBounds": {
                "left": -0.014166704082854352,
                "bottom": -0.045977011494252873,
                "right": 0.66016279783285436,
                "top": 0.75095785440613028
            },
            "atlasBounds": {
                "left": 27.5,
                "bottom": 90.5,
                "right": 49.5,
                "top": 116.5
            }
        },
        {
            "unicode": 36,
            "advance": 0.57080078125,
            "planeBounds": {
                "left": 0.036771693905651347,
                "bottom": -0.10727969348659003,
                "right": 0.52719314984434862,
                "top": 0.8122605363984674
            },
            "atlasBounds": {
                "left": 116.5,
                "bottom": 181.5,
                "right": 132.5,
                "top": 211.5
            }
        },
        {
            "unicode": 37,
            "advance": 0.80712890625,
            "planeBounds": {
                "left": 0.020422690672892777,
                "bottom": -0.045977011494252873,
                "right": 0.78670621557710729,
                "top": 0.7816091954022989
            },
            "atlasBounds": {
                "left": 143.5,
                "bottom": 147.5,
                "right": 168.5,
                "top": 174.5
            }
        },
        {
            "unicode": 38,
            "advance": 0.712890625,
            "planeBounds": {
                "left": 0.022997859794061361,
                "bottom": -0.045977011494252873,
                "right": 0.72797870270593867,
                "top": 0.7816091954022989
            },
            "atlasBounds": {
                "left": 169.5,
                "bottom": 147.5,
                "right": 192.5,
                "top": 174.5
            }
        },
        {
            "unicode": 39,
            "advance": 0.19189453125,
            "planeBounds": {
                "left": 0.01931891313457855,
                "bottom": 0.41379310344827586,
                "right": 0.17257561811542144,
                "top": 0.75095785440613017
            },
            "atlasBounds": {
                "left": 205.5,
                "bottom": 93.5,
                "right": 210.5,
                "top": 104.5
            }
        },
        {
            "unicode": 40,
            "advance": 0.27197265625,
            "planeBounds": {
                "left": 0.0031822467672413517,
                "bottom": -0.1992337164750958,
                "right": 0.27904431573275856,
                "top": 0.75095785440613017
            },
            "atlasBounds": {
                "left": 50.5,
                "bottom": 180.5,
                "right": 59.5,
                "top": 211.5
            }
        },
        {
            "unicode": 41,
            "advance": 0.27197265625,
            "planeBounds": {
                "left": -0.0070716594827586483,
                "bottom": -0.1992337164750958,
                "right": 0.26879040948275856,
                "top": 0.75095785440613017
            },
            "atlasBounds": {
                "left": 60.5,
                "bottom": 180.5,
                "right": 69.5,
                "top": 211.5
            }
        },
        {
            "unicode": 42,
            "advance": 0.55078125,
            "planeBounds": {
                "left": 0.013877664032567105,
                "bottom": 0.29118773946360155,
                "right": 0.53495046096743293,
                "top": 0.8122605363984674
            },
            "atlasBounds": {
                "left": 168.5,
                "bottom": 18.5,
                "right": 185.5,
                "top": 35.5
            }
        },
        {
            "unicode": 43,
            "advance": 0.57080078125,
            "planeBounds": {
                "left": 0.0097824622844828128,
                "bottom": 0.07662835249042145,
                "right": 0.56150660021551735,
                "top": 0.62835249042145591
            },
            "atlasBounds": {
                "left": 111.5,
                "bottom": 17.5,
                "right": 129.5,
                "top": 35.5
            }
        },
        {
            "unicode": 44,
            "advance": 0.21484375,
            "planeBounds": {
                "left": -0.00040128861350573371,
                "bottom": -0.16858237547892721,
                "right": 0.18350675736350575,
                "top": 0.16858237547892718
            },
            "atlasBounds": {
                "left": 205.5,
                "bottom": 105.5,
                "right": 211.5,
                "top": 116.5
            }
        },
        {
            "unicode": 45,
            "advance": 0.32177734375,
            "planeBounds": {
                "left": 0.0076319668941570631,
                "bottom": 0.19923371647509577,
                "right": 0.31414537685584287,
                "top": 0.32183908045977011
            },
            "atlasBounds": {
                "left": 76.5,
                "bottom": 9.5,
                "right": 86.5,
                "top": 13.5
            }
        },
        {
            "unicode": 46,
            "advance": 0.23779296875,
            "planeBounds": {
                "left": 0.042023991259578564,
                "bottom": -0.045977011494252873,
                "right": 0.19528069624042146,
                "top": 0.13793103448275862
            },
            "atlasBounds": {
                "left": 205.5,
                "bottom": 29.5,
                "right": 210.5,
                "top": 35.5
            }
        },
        {
            "unicode": 47,
            "advance": 0.3408203125,
            "planeBounds": {
                "left": -0.028579419600095815,
                "bottom": -0.045977011494252873,
                "right": 0.36988801335009575,
                "top": 0.75095785440613028
            },
            "atlasBounds": {
                "left": 153.5,
                "bottom": 90.5,
                "right": 166.5,
                "top": 116.5
            }
        },
        {
            "unicode": 48,
            "advance": 0.57080078125,
            "planeBounds": {
                "left": 0.025108132782567107,
                "bottom": -0.045977011494252873,
                "right": 0.54618092971743293,
                "top": 0.7816091954022989
            },
            "atlasBounds": {
                "left": 0.5,
                "bottom": 117.5,
                "right": 17.5,
                "top": 144.5
            }
        },
        {
            "unicode": 49,
            "advance": 0.57080078125,
            "planeBounds": {
                "left": 0.061831185644157065,
                "bottom": -0.045977011494252873,
                "right": 0.36834459560584287,
                "top": 0.75095785440613028
            },
            "atlasBounds": {
                "left": 23.5,
                "bottom": 36.5,
                "right": 33.5,
                "top": 62.5
            }
        },
        {
            "unicode": 50,
            "advance": 0.57080078125,
            "planeBounds": {
                "left": 0.018028054657567107,
                "bottom": -0.045977011494252873,
                "right": 0.53910085159243293,
                "top": 0.7816091954022989
            },
            "atlasBounds": {
                "left": 18.5,
                "bottom": 117.5,
                "right": 35.5,
                "top": 144.5
            }
        },
        {
            "unicode": 51,
            "advance": 0.57080078125,
            "planeBounds": {
                "left": 0.012412820282567105,
                "bottom": -0.045977011494252873,
                "right": 0.53348561721743293,
                "top": 0.7816091954022989
            },
            "atlasBounds": {
                "left": 36.5,
                "bottom": 117.5,
                "right": 53.5,
                "top": 144.5
            }
        },
        {
            "unicode": 52,
            "advance": 0.57080078125,
            "planeBounds": {
                "left": -0.017450909961685766,
                "bottom": -0.045977011494252873,
                "right": 0.59557590996168586,
                "top": 0.75095785440613028
            },
            "atlasBounds": {
                "left": 191.5,
                "bottom": 63.5,
                "right": 211.5,
                "top": 89.5
            }
        },
        {
            "unicode": 53,
            "advance": 0.57080078125,
            "planeBounds": {
                "left": 0.028281960907567051,
                "bottom": -0.045977011494252873,
                "right": 0.54935475784243293,
                "top": 0.75095785440613028
            },
            "atlasBounds": {
                "left": 34.5,
                "bottom": 36.5,
                "right": 51.5,
                "top": 62.5
            }
        },
        {
            "unicode": 54,
            "advance": 0.57080078125,
            "planeBounds": {
                "left": 0.029990945282567107,
                "bottom": -0.045977011494252873,
                "right": 0.55106374221743293,
                "top": 0.7816091954022989
            },
            "atlasBounds": {
                "left": 54.5,
                "bottom": 117.5,
                "right": 71.5,
                "top": 144.5
            }
        },
        {
            "unicode": 55,
            "advance": 0.57080078125,
            "planeBounds": {
                "left": 0.0083176185344828128,
                "bottom": -0.045977011494252873,
                "right": 0.56004175646551735,
                "top": 0.75095785440613028
            },
            "atlasBounds": {
                "left": 52.5,
                "bottom": 36.5,
                "right": 70.5,
                "top": 62.5
            }
        },
        {
            "unicode": 56,
            "advance": 0.57080078125,
            "planeBounds": {
                "left": 0.023887429657567107,
                "bottom": -0.045977011494252873,
                "right": 0.54496022659243293,
                "top": 0.7816091954022989
            },
            "atlasBounds": {
                "left": 72.5,
                "bottom": 117.5,
                "right": 89.5,
                "top": 144.5
            }
        },
        {
            "unicode": 57,
            "advance": 0.57080078125,
            "planeBounds": {
                "left": 0.019492898407567107,
                "bottom": -0.045977011494252873,
                "right": 0.54056569534243293,
                "top": 0.7816091954022989
            },
            "atlasBounds": {
                "left": 90.5,
                "bottom": 117.5,
                "right": 107.5,
                "top": 144.5
            }
        },
        {
            "unicode": 58,
            "advance": 0.23779296875,
            "planeBounds": {
                "left": 0.042023991259578564,
                "bottom": -0.045977011494252873,
                "right": 0.19528069624042146,
                "top": 0.56704980842911878
            },
            "atlasBounds": {
                "left": 205.5,
                "bottom": 42.5,
                "right": 210.5,
                "top": 62.5
            }
        },
        {
            "unicode": 59,
            "advance": 0.23779296875,
            "planeBounds": {
                "left": 0.0057022270114942663,
                "bottom": -0.16858237547892721,
                "right": 0.18961027298850575,
                "top": 0.56704980842911878
            },
            "atlasBounds": {
                "left": 71.5,
                "bottom": 38.5,
                "right": 77.5,
                "top": 62.5
            }
        },
        {
            "unicode": 60,
            "advance": 0.57080078125,
            "planeBounds": {
                "left": 0.0097824622844828128,
                "bottom": 0.07662835249042145,
                "right": 0.56150660021551735,
                "top": 0.62835249042145591
            },
            "atlasBounds": {
                "left": 149.5,
                "bottom": 17.5,
                "right": 167.5,
                "top": 35.5
            }
        },
        {
            "unicode": 61,
            "advance": 0.57080078125,
            "planeBounds": {
                "left": 0.0097824622844828128,
                "bottom": 0.19923371647509577,
                "right": 0.56150660021551735,
                "top": 0.50574712643678166
            },
            "atlasBounds": {
                "left": 11.5,
                "bottom": 3.5,
                "right": 29.5,
                "top": 13.5
            }
        },
        {
            "unicode": 62,
            "advance": 0.57080078125,
            "planeBounds": {
                "left": 0.0097824622844828128,
                "bottom": 0.07662835249042145,
                "right": 0.56150660021551735,
                "top": 0.62835249042145591
            },
            "atlasBounds": {
                "left": 130.5,
                "bottom": 17.5,
                "right": 148.5,
                "top": 35.5
            }
        },
        {
            "unicode": 63,
            "advance": 0.4208984375,
            "planeBounds": {
                "left": -0.008260558848180102,
                "bottom": -0.045977011494252873,
                "right": 0.42085821509818,
                "top": 0.7816091954022989
            },
            "atlasBounds": {
                "left": 108.5,
                "bottom": 117.5,
                "right": 122.5,
                "top": 144.5
            }
        },
        {
            "unicode": 64,
            "advance": 0.88623046875,
            "planeBounds": {
                "left": 0.013996460428639902,
                "bottom": -0.13793103448275862,
                "right": 0.87223400832136011,
                "top": 0.75095785440613028
            },
            "atlasBounds": {
                "left": 133.5,
                "bottom": 182.5,
                "right": 161.5,
                "top": 211.5
            }
        },
        {
            "unicode": 65,
            "advance": 0.60009765625,
            "planeBounds": {
                "left": -0.037115922832854358,
                "bottom": -0.045977011494252873,
                "right": 0.63721357908285436,
                "top": 0.75095785440613028
            },
            "atlasBounds": {
                "left": 0.5,
                "bottom": 36.5,
                "right": 22.5,
                "top": 62.5
            }
        },
        {
            "unicode": 66,
            "advance": 0.626953125,
            "planeBounds": {
                "left": 0.060075431034482811,
                "bottom": -0.045977011494252873,
                "right": 0.61179956896551735,
                "top": 0.75095785440613028
            },
            "atlasBounds": {
                "left": 172.5,
                "bottom": 63.5,
                "right": 190.5,
                "top": 89.5
            }
        },
        {
            "unicode": 67,
            "advance": 0.62109375,
            "planeBounds": {
                "left": 0.019902605663314234,
                "bottom": -0.045977011494252873,
                "right": 0.63292942558668586,
                "top": 0.7816091954022989
            },
            "atlasBounds": {
                "left": 123.5,
                "bottom": 117.5,
                "right": 143.5,
                "top": 144.5
            }
        },
        {
            "unicode": 68,
            "advance": 0.7060546875,
            "planeBounds": {
                "left": 0.065556902538314241,
                "bottom": -0.045977011494252873,
                "right": 0.67858372246168586,
                "top": 0.75095785440613028
            },
            "atlasBounds": {
                "left": 137.5,
                "bottom": 63.5,
                "right": 157.5,
                "top": 89.5
            }
        },
        {
            "unicode": 69,
            "advance": 0.5517578125,
            "planeBounds": {
                "left": 0.066257520653735635,
                "bottom": -0.045977011494252873,
                "right": 0.52602763559626431,
                "top": 0.75095785440613028
            },
            "atlasBounds": {
                "left": 121.5,
                "bottom": 63.5,
                "right": 136.5,
                "top": 89.5
            }
        },
        {
            "unicode": 70,
            "advance": 0.501953125,
            "planeBounds": {
                "left": 0.066745801903735635,
                "bottom": -0.045977011494252873,
                "right": 0.52651591684626431,
                "top": 0.75095785440613028
            },
            "atlasBounds": {
                "left": 105.5,
                "bottom": 63.5,
                "right": 120.5,
                "top": 89.5
            }
        },
        {
            "unicode": 71,
            "advance": 0.72314453125,
            "planeBounds": {
                "left": 0.032164825790229945,
                "bottom": -0.045977011494252873,
                "right": 0.67584298670977017,
                "top": 0.7816091954022989
            },
            "atlasBounds": {
                "left": 144.5,
                "bottom": 117.5,
                "right": 165.5,
                "top": 144.5
            }
        },
        {
            "unicode": 72,
            "advance": 0.71923828125,
            "planeBounds": {
                "left": 0.068431401161398536,
                "bottom": -0.045977011494252873,
                "right": 0.65080688008860155,
                "top": 0.75095785440613028
            },
            "atlasBounds": {
                "left": 65.5,
                "bottom": 63.5,
                "right": 84.5,
                "top": 89.5
            }
        },
        {
            "unicode": 73,
            "advance": 0.251953125,
            "planeBounds": {
                "left": 0.064673880507662845,
                "bottom": -0.045977011494252873,
                "right": 0.18727924449233718,
                "top": 0.75095785440613028
            },
            "atlasBounds": {
                "left": 60.5,
                "bottom": 63.5,
                "right": 64.5,
                "top": 89.5
            }
        },
        {
            "unicode": 74,
            "advance": 0.2470703125,
            "planeBounds": {
                "left": -0.12273912685584291,
                "bottom": -0.22988505747126436,
                "right": 0.1837742831058429,
                "top": 0.75095785440613028
            },
            "atlasBounds": {
                "left": 39.5,
                "bottom": 179.5,
                "right": 49.5,
                "top": 211.5
            }
        },
        {
            "unicode": 75,
            "advance": 0.5810546875,
            "planeBounds": {
                "left": 0.065202384159482818,
                "bottom": -0.045977011494252873,
                "right": 0.61692652209051735,
                "top": 0.75095785440613028
            },
            "atlasBounds": {
                "left": 16.5,
                "bottom": 63.5,
                "right": 34.5,
                "top": 89.5
            }
        },
        {
            "unicode": 76,
            "advance": 0.51318359375,
            "planeBounds": {
                "left": 0.066257520653735635,
                "bottom": -0.045977011494252873,
                "right": 0.52602763559626431,
                "top": 0.75095785440613028
            },
            "atlasBounds": {
                "left": 0.5,
                "bottom": 63.5,
                "right": 15.5,
                "top": 89.5
            }
        },
        {
            "unicode": 77,
            "advance": 0.86279296875,
            "planeBounds": {
                "left": 0.063824533045977072,
                "bottom": -0.045977011494252873,
                "right": 0.79945671695402309,
                "top": 0.75095785440613028
            },
            "atlasBounds": {
                "left": 35.5,
                "bottom": 63.5,
                "right": 59.5,
                "top": 89.5
            }
        },
        {
            "unicode": 78,
            "advance": 0.72119140625,
            "planeBounds": {
                "left": 0.069407963661398536,
                "bottom": -0.045977011494252873,
                "right": 0.65178344258860155,
                "top": 0.75095785440613028
            },
            "atlasBounds": {
                "left": 85.5,
                "bottom": 63.5,
                "right": 104.5,
                "top": 89.5
            }
        },
        {
            "unicode": 79,
            "advance": 0.76416015625,
            "planeBounds": {
                "left": 0.029589656669061361,
                "bottom": -0.045977011494252873,
                "right": 0.73457049958093878,
                "top": 0.7816091954022989
            },
            "atlasBounds": {
                "left": 166.5,
                "bottom": 117.5,
                "right": 189.5,
                "top": 144.5
            }
        },
        {
            "unicode": 80,
            "advance": 0.5849609375,
            "planeBounds": {
                "left": 0.055381570282567051,
                "bottom": -0.045977011494252873,
                "right": 0.57645436721743293,
                "top": 0.75095785440613028
            },
            "atlasBounds": {
                "left": 167.5,
                "bottom": 90.5,
                "right": 184.5,
                "top": 116.5
            }
        },
        {
            "unicode": 81,
            "advance": 0.76416015625,
            "planeBounds": {
                "left": 0.029589656669061361,
                "bottom": -0.22988505747126436,
                "right": 0.73457049958093878,
                "top": 0.7816091954022989
            },
            "atlasBounds": {
                "left": 15.5,
                "bottom": 178.5,
                "right": 38.5,
                "top": 211.5
            }
        },
        {
            "unicode": 82,
            "advance": 0.59423828125,
            "planeBounds": {
                "left": 0.060563712284482811,
                "bottom": -0.045977011494252873,
                "right": 0.61228785021551735,
                "top": 0.75095785440613028
            },
            "atlasBounds": {
                "left": 134.5,
                "bottom": 90.5,
                "right": 152.5,
                "top": 116.5
            }
        },
        {
            "unicode": 83,
            "advance": 0.544921875,
            "planeBounds": {
                "left": 0.014121804657567105,
                "bottom": -0.045977011494252873,
                "right": 0.53519460159243293,
                "top": 0.7816091954022989
            },
            "atlasBounds": {
                "left": 190.5,
                "bottom": 117.5,
                "right": 207.5,
                "top": 144.5
            }
        },
        {
            "unicode": 84,
            "advance": 0.52392578125,
            "planeBounds": {
                "left": -0.029224848838601478,
                "bottom": -0.045977011494252873,
                "right": 0.55315063008860155,
                "top": 0.75095785440613028
            },
            "atlasBounds": {
                "left": 93.5,
                "bottom": 90.5,
                "right": 112.5,
                "top": 116.5
            }
        },
        {
            "unicode": 85,
            "advance": 0.71923828125,
            "planeBounds": {
                "left": 0.052861590038314234,
                "bottom": -0.045977011494252873,
                "right": 0.66588840996168586,
                "top": 0.75095785440613028
            },
            "atlasBounds": {
                "left": 72.5,
                "bottom": 90.5,
                "right": 92.5,
                "top": 116.5
            }
        },
        {
            "unicode": 86,
            "advance": 0.5771484375,
            "planeBounds": {
                "left": -0.033264861709770062,
                "bottom": -0.045977011494252873,
                "right": 0.61041329920977017,
                "top": 0.75095785440613028
            },
            "atlasBounds": {
                "left": 50.5,
                "bottom": 90.5,
                "right": 71.5,
                "top": 116.5
            }
        },
        {
            "unicode": 87,
            "advance": 0.89208984375,
            "planeBounds": {
                "left": -0.013725193067528679,
                "bottom": -0.045977011494252873,
                "right": 0.90581503681752884,
                "top": 0.75095785440613028
            },
            "atlasBounds": {
                "left": 181.5,
                "bottom": 185.5,
                "right": 211.5,
                "top": 211.5
            }
        },
        {
            "unicode": 88,
            "advance": 0.5380859375,
            "planeBounds": {
                "left": -0.037470441211685766,
                "bottom": -0.045977011494252873,
                "right": 0.57555637871168586,
                "top": 0.75095785440613028
            },
            "atlasBounds": {
                "left": 6.5,
                "bottom": 90.5,
                "right": 26.5,
                "top": 116.5
            }
        },
        {
            "unicode": 89,
            "advance": 0.52783203125,
            "planeBounds": {
                "left": -0.042597394336685766,
                "bottom": -0.045977011494252873,
                "right": 0.57042942558668586,
                "top": 0.75095785440613028
            },
            "atlasBounds": {
                "left": 113.5,
                "bottom": 90.5,
                "right": 133.5,
                "top": 116.5
            }
        },
        {
            "unicode": 90,
            "advance": 0.576171875,
            "planeBounds": {
                "left": -0.0031018019636014759,
                "bottom": -0.045977011494252873,
                "right": 0.57927367696360155,
                "top": 0.75095785440613028
            },
            "atlasBounds": {
                "left": 185.5,
                "bottom": 90.5,
                "right": 204.5,
                "top": 116.5
            }
        },
        {
            "unicode": 91,
            "advance": 0.31884765625,
            "planeBounds": {
                "left": 0.051522090517241353,
                "bottom": -0.1992337164750958,
                "right": 0.32738415948275856,
                "top": 0.75095785440613017
            },
            "atlasBounds": {
                "left": 83.5,
                "bottom": 180.5,
                "right": 92.5,
                "top": 211.5
            }
        },
        {
            "unicode": 92,
            "advance": 0.3408203125,
            "planeBounds": {
                "left": -0.028579419600095815,
                "bottom": -0.045977011494252873,
                "right": 0.36988801335009575,
                "top": 0.75095785440613028
            },
            "atlasBounds": {
                "left": 158.5,
                "bottom": 63.5,
                "right": 171.5,
                "top": 89.5
            }
        },
        {
            "unicode": 93,
            "advance": 0.31884765625,
            "planeBounds": {
                "left": -0.0085365032327586483,
                "bottom": -0.1992337164750958,
                "right": 0.26732556573275856,
                "top": 0.75095785440613017
            },
            "atlasBounds": {
                "left": 93.5,
                "bottom": 180.5,
                "right": 102.5,
                "top": 211.5
            }
        },
        {
            "unicode": 94,
            "advance": 0.57080078125,
            "planeBounds": {
                "left": 0.0095383216594828128,
                "bottom": 0.22988505747126436,
                "right": 0.56126245959051735,
                "top": 0.75095785440613028
            },
            "atlasBounds": {
                "left": 186.5,
                "bottom": 18.5,
                "right": 204.5,
                "top": 35.5
            }
        },
        {
            "unicode": 95,
            "advance": 0.4111328125,
            "planeBounds": {
                "left": -0.039644321719348681,
                "bottom": -0.16858237547892721,
                "right": 0.45077713421934856,
                "top": -0.045977011494252873
            },
            "atlasBounds": {
                "left": 59.5,
                "bottom": 9.5,
                "right": 75.5,
                "top": 13.5
            }
        },
        {
            "unicode": 96,
            "advance": 0.5771484375,
            "planeBounds": {
                "left": 0.14746935614224135,
                "bottom": 0.56704980842911878,
                "right": 0.42333142510775856,
                "top": 0.8122605363984674
            },
            "atlasBounds": {
                "left": 30.5,
                "bottom": 5.5,
                "right": 39.5,
                "top": 13.5
            }
        },
        {
            "unicode": 97,
            "advance": 0.52978515625,
            "planeBounds": {
                "left": 0.0021037251556513138,
                "bottom": -0.045977011494252873,
                "right": 0.49252518109434856,
                "top": 0.5977011494252874
            },
            "atlasBounds": {
                "left": 188.5,
                "bottom": 41.5,
                "right": 204.5,
                "top": 62.5
            }
        },
        {
            "unicode": 98,
            "advance": 0.59521484375,
            "planeBounds": {
                "left": 0.052451882782567107,
                "bottom": -0.045977011494252873,
                "right": 0.57352467971743293,
                "top": 0.8122605363984674
            },
            "atlasBounds": {
                "left": 54.5,
                "bottom": 146.5,
                "right": 71.5,
                "top": 174.5
            }
        },
        {
            "unicode": 99,
            "advance": 0.47509765625,
            "planeBounds": {
                "left": 0.019138380028735608,
                "bottom": -0.045977011494252873,
                "right": 0.47890849497126431,
                "top": 0.5977011494252874
            },
            "atlasBounds": {
                "left": 145.5,
                "bottom": 41.5,
                "right": 160.5,
                "top": 62.5
            }
        },
        {
            "unicode": 100,
            "advance": 0.59521484375,
            "planeBounds": {
                "left": 0.021446023407567107,
                "bottom": -0.045977011494252873,
                "right": 0.54251882034243293,
                "top": 0.8122605363984674
            },
            "atlasBounds": {
                "left": 72.5,
                "bottom": 146.5,
                "right": 89.5,
                "top": 174.5
            }
        },
        {
            "unicode": 101,
            "advance": 0.548828125,
            "planeBounds": {
                "left": 0.014121804657567049,
                "bottom": -0.045977011494252873,
                "right": 0.53519460159243293,
                "top": 0.5977011494252874
            },
            "atlasBounds": {
                "left": 110.5,
                "bottom": 41.5,
                "right": 127.5,
                "top": 62.5
            }
        },
        {
            "unicode": 102,
            "advance": 0.2998046875,
            "planeBounds": {
                "left": -0.030477355723180104,
                "bottom": -0.045977011494252873,
                "right": 0.39864141822318,
                "top": 0.8122605363984674
            },
            "atlasBounds": {
                "left": 111.5,
                "bottom": 146.5,
                "right": 125.5,
                "top": 174.5
            }
        },
        {
            "unicode": 103,
            "advance": 0.52294921875,
            "planeBounds": {
                "left": -0.013410897090517187,
                "bottom": -0.29118773946360149,
                "right": 0.53831324084051735,
                "top": 0.59770114942528729
            },
            "atlasBounds": {
                "left": 162.5,
                "bottom": 182.5,
                "right": 180.5,
                "top": 211.5
            }
        },
        {
            "unicode": 104,
            "advance": 0.58984375,
            "planeBounds": {
                "left": 0.052640834530651347,
                "bottom": -0.045977011494252873,
                "right": 0.54306229046934862,
                "top": 0.8122605363984674
            },
            "atlasBounds": {
                "left": 126.5,
                "bottom": 146.5,
                "right": 142.5,
                "top": 174.5
            }
        },
        {
            "unicode": 105,
            "advance": 0.22607421875,
            "planeBounds": {
                "left": 0.03689703813457855,
                "bottom": -0.045977011494252873,
                "right": 0.19015374311542144,
                "top": 0.7816091954022989
            },
            "atlasBounds": {
                "left": 193.5,
                "bottom": 147.5,
                "right": 198.5,
                "top": 174.5
            }
        },
        {
            "unicode": 106,
            "advance": 0.22607421875,
            "planeBounds": {
                "left": -0.089347050107758605,
                "bottom": -0.29118773946360149,
                "right": 0.18651501885775859,
                "top": 0.78160919540229878
            },
            "atlasBounds": {
                "left": 5.5,
                "bottom": 176.5,
                "right": 14.5,
                "top": 211.5
            }
        },
        {
            "unicode": 107,
            "advance": 0.48388671875,
            "planeBounds": {
                "left": 0.056491895653735635,
                "bottom": -0.045977011494252873,
                "right": 0.51626201059626431,
                "top": 0.8122605363984674
            },
            "atlasBounds": {
                "left": 95.5,
                "bottom": 146.5,
                "right": 110.5,
                "top": 174.5
            }
        },
        {
            "unicode": 108,
            "advance": 0.22607421875,
            "planeBounds": {
                "left": 0.051734427382662838,
                "bottom": -0.045977011494252873,
                "right": 0.17433979136733718,
                "top": 0.8122605363984674
            },
            "atlasBounds": {
                "left": 90.5,
                "bottom": 146.5,
                "right": 94.5,
                "top": 174.5
            }
        },
        {
            "unicode": 109,
            "advance": 0.8828125,
            "planeBounds": {
                "left": 0.045868504549808488,
                "bottom": -0.045977011494252873,
                "right": 0.8428033704501916,
                "top": 0.5977011494252874
            },
            "atlasBounds": {
                "left": 161.5,
                "bottom": 41.5,
                "right": 187.5,
                "top": 62.5
            }
        },
        {
            "unicode": 110,
            "advance": 0.58984375,
            "planeBounds": {
                "left": 0.052640834530651347,
                "bottom": -0.045977011494252873,
                "right": 0.54306229046934862,
                "top": 0.5977011494252874
            },
            "atlasBounds": {
                "left": 128.5,
                "bottom": 41.5,
                "right": 144.5,
                "top": 62.5
            }
        },
        {
            "unicode": 111,
            "advance": 0.5859375,
            "planeBounds": {
                "left": 0.017106681034482811,
                "bottom": -0.045977011494252873,
                "right": 0.56883081896551735,
                "top": 0.5977011494252874
            },
            "atlasBounds": {
                "left": 78.5,
                "bottom": 41.5,
                "right": 96.5,
                "top": 62.5
            }
        },
        {
            "unicode": 112,
            "advance": 0.59521484375,
            "planeBounds": {
                "left": 0.052451882782567107,
                "bottom": -0.29118773946360149,
                "right": 0.57352467971743293,
                "top": 0.59770114942528729
            },
            "atlasBounds": {
                "left": 18.5,
                "bottom": 145.5,
                "right": 35.5,
                "top": 174.5
            }
        },
        {
            "unicode": 113,
            "advance": 0.59521484375,
            "planeBounds": {
                "left": 0.021446023407567107,
                "bottom": -0.29118773946360149,
                "right": 0.54251882034243293,
                "top": 0.59770114942528729
            },
            "atlasBounds": {
                "left": 0.5,
                "bottom": 145.5,
                "right": 17.5,
                "top": 174.5
            }
        },
        {
            "unicode": 114,
            "advance": 0.38916015625,
            "planeBounds": {
                "left": 0.045584141522988481,
                "bottom": -0.045977011494252873,
                "right": 0.41340023347701144,
                "top": 0.5977011494252874
            },
            "atlasBounds": {
                "left": 97.5,
                "bottom": 41.5,
                "right": 109.5,
                "top": 62.5
            }
        },
        {
            "unicode": 115,
            "advance": 0.4658203125,
            "planeBounds": {
                "left": -0.00039286997126439412,
                "bottom": -0.045977011494252873,
                "right": 0.45937724497126431,
                "top": 0.5977011494252874
            },
            "atlasBounds": {
                "left": 0.5,
                "bottom": 14.5,
                "right": 15.5,
                "top": 35.5
            }
        },
        {
            "unicode": 116,
            "advance": 0.3349609375,
            "planeBounds": {
                "left": -0.023263514727011526,
                "bottom": -0.045977011494252873,
                "right": 0.34455257722701144,
                "top": 0.72030651340996166
            },
            "atlasBounds": {
                "left": 199.5,
                "bottom": 149.5,
                "right": 211.5,
                "top": 174.5
            }
        },
        {
            "unicode": 117,
            "advance": 0.58984375,
            "planeBounds": {
                "left": 0.046781459530651347,
                "bottom": -0.045977011494252873,
                "right": 0.53720291546934862,
                "top": 0.56704980842911878
            },
            "atlasBounds": {
                "left": 16.5,
                "bottom": 15.5,
                "right": 32.5,
                "top": 35.5
            }
        },
        {
            "unicode": 118,
            "advance": 0.458984375,
            "planeBounds": {
                "left": -0.031044210967432949,
                "bottom": -0.045977011494252873,
                "right": 0.49002858596743293,
                "top": 0.56704980842911878
            },
            "atlasBounds": {
                "left": 67.5,
                "bottom": 15.5,
                "right": 84.5,
                "top": 35.5
            }
        },
        {
            "unicode": 119,
            "advance": 0.72314453125,
            "planeBounds": {
                "left": -0.02156949682710723,
                "bottom": -0.045977011494252873,
                "right": 0.74471402807710729,
                "top": 0.56704980842911878
            },
            "atlasBounds": {
                "left": 85.5,
                "bottom": 15.5,
                "right": 110.5,
                "top": 35.5
            }
        },
        {
            "unicode": 120,
            "advance": 0.498046875,
            "planeBounds": {
                "left": -0.011512960967432895,
                "bottom": -0.045977011494252873,
                "right": 0.50955983596743293,
                "top": 0.56704980842911878
            },
            "atlasBounds": {
                "left": 33.5,
                "bottom": 15.5,
                "right": 50.5,
                "top": 35.5
            }
        },
        {
            "unicode": 121,
            "advance": 0.458984375,
            "planeBounds": {
                "left": -0.031044210967432949,
                "bottom": -0.29118773946360149,
                "right": 0.49002858596743293,
                "top": 0.56704980842911867
            },
            "atlasBounds": {
                "left": 36.5,
                "bottom": 146.5,
                "right": 53.5,
                "top": 174.5
            }
        },
        {
            "unicode": 122,
            "advance": 0.4609375,
            "planeBounds": {
                "left": -0.00039286997126439412,
                "bottom": -0.045977011494252873,
                "right": 0.45937724497126431,
                "top": 0.56704980842911878
            },
            "atlasBounds": {
                "left": 51.5,
                "bottom": 15.5,
                "right": 66.5,
                "top": 35.5
            }
        },
        {
            "unicode": 123,
            "advance": 0.35302734375,
            "planeBounds": {
                "left": -0.010079920977011521,
                "bottom": -0.1992337164750958,
                "right": 0.35773617097701144,
                "top": 0.75095785440613017
            },
            "atlasBounds": {
                "left": 70.5,
                "bottom": 180.5,
                "right": 82.5,
                "top": 211.5
            }
        },
        {
            "unicode": 124,
            "advance": 0.541015625,
            "planeBounds": {
                "left": 0.20920513050766282,
                "bottom": -0.29118773946360149,
                "right": 0.33181049449233713,
                "top": 0.8122605363984674
            },
            "atlasBounds": {
                "left": 0.5,
                "bottom": 175.5,
                "right": 4.5,
                "top": 211.5
            }
        },
        {
            "unicode": 125,
            "advance": 0.35302734375,
            "planeBounds": {
                "left": -0.0047088272270115212,
                "bottom": -0.1992337164750958,
                "right": 0.36310726472701144,
                "top": 0.75095785440613017
            },
            "atlasBounds": {
                "left": 103.5,
                "bottom": 180.5,
                "right": 115.5,
                "top": 211.5
            }
        },
        {
            "unicode": 126,
            "advance": 0.57080078125,
            "planeBounds": {
                "left": 0.0097824622844828128,
                "bottom": 0.26053639846743293,
                "right": 0.56150660021551735,
                "top": 0.44444444444444442
            },
            "atlasBounds": {
                "left": 40.5,
                "bottom": 7.5,
                "right": 58.5,
                "top": 13.5
            }
        }
    ],
    "kerning": [
        {
            "unicode1": 34,
            "unicode2": 65,
            "advance": -0.06982421875
        },
        {
            "unicode1": 34,
            "unicode2": 84,
            "advance": 0.02001953125
        },
        {
            "unicode1": 34,
            "unicode2": 86,
            "advance": 0.02001953125
        },
        {
            "unicode1": 34,
            "unicode2": 87,
            "advance": 0.02001953125
        },
        {
            "unicode1": 34,
            "unicode2": 89,
            "advance": 0.009765625
        },
        {
            "unicode1": 34,
            "unicode2": 97,
            "advance": -0.0400390625
        },
        {
            "unicode1": 34,
            "unicode2": 99,
            "advance": -0.06005859375
        },
        {
            "unicode1": 34,
            "unicode2": 100,
            "advance": -0.06005859375
        },
        {
            "unicode1": 34,
            "unicode2": 101,
            "advance": -0.06005859375
        },
        {
            "unicode1": 34,
            "unicode2": 103,
            "advance": -0.02978515625
        },
        {
            "unicode1": 34,
            "unicode2": 109,
            "advance": -0.02978515625
        },
        {
            "unicode1": 34,
            "unicode2": 110,
            "advance": -0.02978515625
        },
        {
            "unicode1": 34,
            "unicode2": 111,
            "advance": -0.06005859375
        },
        {
            "unicode1": 34,
            "unicode2": 112,
            "advance": -0.02978515625
        },
        {
            "unicode1": 34,
            "unicode2": 113,
            "advance": -0.06005859375
        },
        {
            "unicode1": 34,
            "unicode2": 114,
            "advance": -0.02978515625
        },
        {
            "unicode1": 34,
            "unicode2": 115,
            "advance": -0.02978515625
        },
        {
            "unicode1": 34,
            "unicode2": 117,
            "advance": -0.02978515625
        },
        {
            "unicode1": 39,
            "unicode2": 65,
            "advance": -0.06982421875
        },
        {
            "unicode1": 39,
            "unicode2": 84,
            "advance": 0.02001953125
        },
        {
            "unicode1": 39,
            "unicode2": 86,
            "advance": 0.02001953125
        },
        {
            "unicode1": 39,
            "unicode2": 87,
            "advance": 0.02001953125
        },
        {
            "unicode1": 39,
            "unicode2": 89,
            "advance": 0.009765625
        },
        {
            "unicode1": 39,
            "unicode2": 97,
            "advance": -0.0400390625
        },
        {
            "unicode1": 39,
            "unicode2": 99,
            "advance": -0.06005859375
        },
        {
            "unicode1": 39,
            "unicode2": 100,
            "advance": -0.06005859375
        },
        {
            "unicode1": 39,
            "unicode2": 101,
            "advance": -0.06005859375
        },
        {
            "unicode1": 39,
            "unicode2": 103,
            "advance": -0.02978515625
        },
        {
            "unicode1": 39,
            "unicode2": 109,
            "advance": -0.02978515625
        },
        {
            "unicode1": 39,
            "unicode2": 110,
            "advance": -0.02978515625
        },
        {
            "unicode1": 39,
            "unicode2": 111,
            "advance": -0.06005859375
        },
        {
            "unicode1": 39,
            "unicode2": 112,
            "advance": -0.02978515625
        },
        {
            "unicode1": 39,
            "unicode2": 113,
            "advance": -0.06005859375
        },
        {
            "unicode1": 39,
            "unicode2": 114,
            "advance": -0.02978515625
        },
        {
            "unicode1": 39,
            "unicode2": 115,
            "advance": -0.02978515625
        },
        {
            "unicode1": 39,
            "unicode2": 117,
            "advance": -0.02978515625
        },
        {
            "unicode1": 40,
            "unicode2": 74,
            "advance": 0.08984375
        },
        {
            "unicode1": 44,
            "unicode2": 67,
            "advance": -0.0498046875
        },
        {
            "unicode1": 44,
            "unicode2": 71,
            "advance": -0.0498046875
        },
        {
            "unicode1": 44,
            "unicode2": 79,
            "advance": -0.0498046875
        },
        {
            "unicode1": 44,
            "unicode2": 81,
            "advance": -0.0498046875
        },
        {
            "unicode1": 44,
            "unicode2": 84,
            "advance": -0.06982421875
        },
        {
            "unicode1": 44,
            "unicode2": 85,
            "advance": -0.02001953125
        },
        {
            "unicode1": 44,
            "unicode2": 86,
            "advance": -0.06005859375
        },
        {
            "unicode1": 44,
            "unicode2": 87,
            "advance": -0.06005859375
        },
        {
            "unicode1": 44,
            "unicode2": 89,
            "advance": -0.06005859375
        },
        {
            "unicode1": 45,
            "unicode2": 84,
            "advance": -0.0400390625
        },
        {
            "unicode1": 46,
            "unicode2": 67,
            "advance": -0.0498046875
        },
        {
            "unicode1": 46,
            "unicode2": 71,
            "advance": -0.0498046875
        },
        {
            "unicode1": 46,
            "unicode2": 79,
            "advance": -0.0498046875
        },
        {
            "unicode1": 46,
            "unicode2": 81,
            "advance": -0.0498046875
        },
        {
            "unicode1": 46,
            "unicode2": 84,
            "advance": -0.06982421875
        },
        {
            "unicode1": 46,
            "unicode2": 85,
            "advance": -0.02001953125
        },
        {
            "unicode1": 46,
            "unicode2": 86,
            "advance": -0.06005859375
        },
        {
            "unicode1": 46,
            "unicode2": 87,
            "advance": -0.06005859375
        },
        {
            "unicode1": 46,
            "unicode2": 89,
            "advance": -0.06005859375
        },
        {
            "unicode1": 65,
            "unicode2": 34,
            "advance": -0.06982421875
        },
        {
            "unicode1": 65,
            "unicode2": 39,
            "advance": -0.06982421875
        },
        {
            "unicode1": 65,
            "unicode2": 67,
            "advance": -0.02001953125
        },
        {
            "unicode1": 65,
            "unicode2": 71,
            "advance": -0.02001953125
        },
        {
            "unicode1": 65,
            "unicode2": 74,
            "advance": 0.1298828125
        },
        {
            "unicode1": 65,
            "unicode2": 79,
            "advance": -0.02001953125
        },
        {
            "unicode1": 65,
            "unicode2": 81,
            "advance": -0.02001953125
        },
        {
            "unicode1": 65,
            "unicode2": 84,
            "advance": -0.06982421875
        },
        {
            "unicode1": 65,
            "unicode2": 86,
            "advance": -0.0400390625
        },
        {
            "unicode1": 65,
            "unicode2": 87,
            "advance": -0.0400390625
        },
        {
            "unicode1": 65,
            "unicode2": 89,
            "advance": -0.06005859375
        },
        {
            "unicode1": 66,
            "unicode2": 44,
            "advance": -0.0400390625
        },
        {
            "unicode1": 66,
            "unicode2": 46,
            "advance": -0.0400390625
        },
        {
            "unicode1": 66,
            "unicode2": 65,
            "advance": -0.02001953125
        },
        {
            "unicode1": 66,
            "unicode2": 84,
            "advance": -0.02978515625
        },
        {
            "unicode1": 66,
            "unicode2": 86,
            "advance": -0.009765625
        },
        {
            "unicode1": 66,
            "unicode2": 87,
            "advance": -0.009765625
        },
        {
            "unicode1": 66,
            "unicode2": 88,
            "advance": -0.02001953125
        },
        {
            "unicode1": 66,
            "unicode2": 89,
            "advance": -0.009765625
        },
        {
            "unicode1": 66,
            "unicode2": 90,
            "advance": -0.009765625
        },
        {
            "unicode1": 67,
            "unicode2": 67,
            "advance": -0.02001953125
        },
        {
            "unicode1": 67,
            "unicode2": 71,
            "advance": -0.02001953125
        },
        {
            "unicode1": 67,
            "unicode2": 79,
            "advance": -0.02001953125
        },
        {
            "unicode1": 67,
            "unicode2": 81,
            "advance": -0.02001953125
        },
        {
            "unicode1": 68,
            "unicode2": 44,
            "advance": -0.0400390625
        },
        {
            "unicode1": 68,
            "unicode2": 46,
            "advance": -0.0400390625
        },
        {
            "unicode1": 68,
            "unicode2": 65,
            "advance": -0.02001953125
        },
        {
            "unicode1": 68,
            "unicode2": 84,
            "advance": -0.02978515625
        },
        {
            "unicode1": 68,
            "unicode2": 86,
            "advance": -0.009765625
        },
        {
            "unicode1": 68,
            "unicode2": 87,
            "advance": -0.009765625
        },
        {
            "unicode1": 68,
            "unicode2": 88,
            "advance": -0.02001953125
        },
        {
            "unicode1": 68,
            "unicode2": 89,
            "advance": -0.009765625
        },
        {
            "unicode1": 68,
            "unicode2": 90,
            "advance": -0.009765625
        },
        {
            "unicode1": 69,
            "unicode2": 74,
            "advance": 0.06005859375
        },
        {
            "unicode1": 70,
            "unicode2": 44,
            "advance": -0.06005859375
        },
        {
            "unicode1": 70,
            "unicode2": 46,
            "advance": -0.06005859375
        },
        {
            "unicode1": 70,
            "unicode2": 63,
            "advance": 0.02001953125
        },
        {
            "unicode1": 70,
            "unicode2": 65,
            "advance": -0.02001953125
        },
        {
            "unicode1": 75,
            "unicode2": 67,
            "advance": -0.02001953125
        },
        {
            "unicode1": 75,
            "unicode2": 71,
            "advance": -0.02001953125
        },
        {
            "unicode1": 75,
            "unicode2": 79,
            "advance": -0.02001953125
        },
        {
            "unicode1": 75,
            "unicode2": 81,
            "advance": -0.02001953125
        },
        {
            "unicode1": 76,
            "unicode2": 34,
            "advance": -0.080078125
        },
        {
            "unicode1": 76,
            "unicode2": 39,
            "advance": -0.080078125
        },
        {
            "unicode1": 76,
            "unicode2": 67,
            "advance": -0.02001953125
        },
        {
            "unicode1": 76,
            "unicode2": 71,
            "advance": -0.02001953125
        },
        {
            "unicode1": 76,
            "unicode2": 79,
            "advance": -0.02001953125
        },
        {
            "unicode1": 76,
            "unicode2": 81,
            "advance": -0.02001953125
        },
        {
            "unicode1": 76,
            "unicode2": 84,
            "advance": -0.02001953125
        },
        {
            "unicode1": 76,
            "unicode2": 85,
            "advance": -0.009765625
        },
        {
            "unicode1": 76,
            "unicode2": 86,
            "advance": -0.02001953125
        },
        {
            "unicode1": 76,
            "unicode2": 87,
            "advance": -0.02001953125
        },
        {
            "unicode1": 76,
            "unicode2": 89,
            "advance": -0.02978515625
        },
        {
            "unicode1": 79,
            "unicode2": 44,
            "advance": -0.0400390625
        },
        {
            "unicode1": 79,
            "unicode2": 46,
            "advance": -0.0400390625
        },
        {
            "unicode1": 79,
            "unicode2": 65,
            "advance": -0.02001953125
        },
        {
            "unicode1": 79,
            "unicode2": 84,
            "advance": -0.02978515625
        },
        {
            "unicode1": 79,
            "unicode2": 86,
            "advance": -0.009765625
        },
        {
            "unicode1": 79,
            "unicode2": 87,
            "advance": -0.009765625
        },
        {
            "unicode1": 79,
            "unicode2": 88,
            "advance": -0.02001953125
        },
        {
            "unicode1": 79,
            "unicode2": 89,
            "advance": -0.009765625
        },
        {
            "unicode1": 79,
            "unicode2": 90,
            "advance": -0.009765625
        },
        {
            "unicode1": 80,
            "unicode2": 44,
            "advance": -0.1298828125
        },
        {
            "unicode1": 80,
            "unicode2": 46,
            "advance": -0.1298828125
        },
        {
            "unicode1": 80,
            "unicode2": 65,
            "advance": -0.0498046875
        },
        {
            "unicode1": 80,
            "unicode2": 88,
            "advance": -0.02001953125
        },
        {
            "unicode1": 80,
            "unicode2": 90,
            "advance": -0.009765625
        },
        {
            "unicode1": 81,
            "unicode2": 44,
            "advance": -0.0400390625
        },
        {
            "unicode1": 81,
            "unicode2": 46,
            "advance": -0.0400390625
        },
        {
            "unicode1": 81,
            "unicode2": 65,
            "advance": -0.02001953125
        },
        {
            "unicode1": 81,
            "unicode2": 84,
            "advance": -0.02978515625
        },
        {
            "unicode1": 81,
            "unicode2": 86,
            "advance": -0.009765625
        },
        {
            "unicode1": 81,
            "unicode2": 87,
            "advance": -0.009765625
        },
        {
            "unicode1": 81,
            "unicode2": 88,
            "advance": -0.02001953125
        },
        {
            "unicode1": 81,
            "unicode2": 89,
            "advance": -0.009765625
        },
        {
            "unicode1": 81,
            "unicode2": 90,
            "advance": -0.009765625
        },
        {
            "unicode1": 84,
            "unicode2": 44,
            "advance": -0.06005859375
        },
        {
            "unicode1": 84,
            "unicode2": 45,
            "advance": -0.0400390625
        },
        {
            "unicode1": 84,
            "unicode2": 46,
            "advance": -0.06005859375
        },
        {
            "unicode1": 84,
            "unicode2": 63,
            "advance": 0.02001953125
        },
        {
            "unicode1": 84,
            "unicode2": 65,
            "advance": -0.06982421875
        },
        {
            "unicode1": 84,
            "unicode2": 67,
            "advance": -0.02001953125
        },
        {
            "unicode1": 84,
            "unicode2": 71,
            "advance": -0.02001953125
        },
        {
            "unicode1": 84,
            "unicode2": 79,
            "advance": -0.02001953125
        },
        {
            "unicode1": 84,
            "unicode2": 81,
            "advance": -0.02001953125
        },
        {
            "unicode1": 84,
            "unicode2": 84,
            "advance": 0.02001953125
        },
        {
            "unicode1": 84,
            "unicode2": 97,
            "advance": -0.080078125
        },
        {
            "unicode1": 84,
            "unicode2": 99,
            "advance": -0.06982421875
        },
        {
            "unicode1": 84,
            "unicode2": 100,
            "advance": -0.06982421875
        },
        {
            "unicode1": 84,
            "unicode2": 101,
            "advance": -0.06982421875
        },
        {
            "unicode1": 84,
            "unicode2": 103,
            "advance": -0.06982421875
        },
        {
            "unicode1": 84,
            "unicode2": 109,
            "advance": -0.0498046875
        },
        {
            "unicode1": 84,
            "unicode2": 110,
            "advance": -0.0498046875
        },
        {
            "unicode1": 84,
            "unicode2": 111,
            "advance": -0.06982421875
        },
        {
            "unicode1": 84,
            "unicode2": 112,
            "advance": -0.0498046875
        },
        {
            "unicode1": 84,
            "unicode2": 113,
            "advance": -0.06982421875
        },
        {
            "unicode1": 84,
            "unicode2": 114,
            "advance": -0.0498046875
        },
        {
            "unicode1": 84,
            "unicode2": 115,
            "advance": -0.06005859375
        },
        {
            "unicode1": 84,
            "unicode2": 117,
            "advance": -0.0498046875
        },
        {
            "unicode1": 84,
            "unicode2": 118,
            "advance": -0.02001953125
        },
        {
            "unicode1": 84,
            "unicode2": 119,
            "advance": -0.02001953125
        },
        {
            "unicode1": 84,
            "unicode2": 120,
            "advance": -0.02001953125
        },
        {
            "unicode1": 84,
            "unicode2": 121,
            "advance": -0.02001953125
        },
        {
            "unicode1": 84,
            "unicode2": 122,
            "advance": -0.0400390625
        },
        {
            "unicode1": 85,
            "unicode2": 44,
            "advance": -0.02001953125
        },
        {
            "unicode1": 85,
            "unicode2": 46,
            "advance": -0.02001953125
        },
        {
            "unicode1": 85,
            "unicode2": 65,
            "advance": -0.009765625
        },
        {
            "unicode1": 86,
            "unicode2": 44,
            "advance": -0.0498046875
        },
        {
            "unicode1": 86,
            "unicode2": 46,
            "advance": -0.0498046875
        },
        {
            "unicode1": 86,
            "unicode2": 63,
            "advance": 0.02001953125
        },
        {
            "unicode1": 86,
            "unicode2": 65,
            "advance": -0.0400390625
        },
        {
            "unicode1": 86,
            "unicode2": 67,
            "advance": -0.009765625
        },
        {
            "unicode1": 86,
            "unicode2": 71,
            "advance": -0.009765625
        },
        {
            "unicode1": 86,
            "unicode2": 79,
            "advance": -0.009765625
        },
        {
            "unicode1": 86,
            "unicode2": 81,
            "advance": -0.009765625
        },
        {
            "unicode1": 86,
            "unicode2": 97,
            "advance": -0.02001953125
        },
        {
            "unicode1": 86,
            "unicode2": 99,
            "advance": -0.02001953125
        },
        {
            "unicode1": 86,
            "unicode2": 100,
            "advance": -0.02001953125
        },
        {
            "unicode1": 86,
            "unicode2": 101,
            "advance": -0.02001953125
        },
        {
            "unicode1": 86,
            "unicode2": 103,
            "advance": -0.009765625
        },
        {
            "unicode1": 86,
            "unicode2": 109,
            "advance": -0.009765625
        },
        {
            "unicode1": 86,
            "unicode2": 110,
            "advance": -0.009765625
        },
        {
            "unicode1": 86,
            "unicode2": 111,
            "advance": -0.02001953125
        },
        {
            "unicode1": 86,
            "unicode2": 112,
            "advance": -0.009765625
        },
        {
            "unicode1": 86,
            "unicode2": 113,
            "advance": -0.02001953125
        },
        {
            "unicode1": 86,
            "unicode2": 114,
            "advance": -0.009765625
        },
        {
            "unicode1": 86,
            "unicode2": 115,
            "advance": -0.009765625
        },
        {
            "unicode1": 86,
            "unicode2": 117,
            "advance": -0.009765625
        },
        {
            "unicode1": 87,
            "unicode2": 44,
            "advance": -0.0498046875
        },
        {
            "unicode1": 87,
            "unicode2": 46,
            "advance": -0.0498046875
        },
        {
            "unicode1": 87,
            "unicode2": 63,
            "advance": 0.02001953125
        },
        {
            "unicode1": 87,
            "unicode2": 65,
            "advance": -0.0400390625
        },
        {
            "unicode1": 87,
            "unicode2": 67,
            "advance": -0.009765625
        },
        {
            "unicode1": 87,
            "unicode2": 71,
            "advance": -0.009765625
        },
        {
            "unicode1": 87,
            "unicode2": 79,
            "advance": -0.009765625
        },
        {
            "unicode1": 87,
            "unicode2": 81,
            "advance": -0.009765625
        },
        {
            "unicode1": 87,
            "unicode2": 97,
            "advance": -0.02001953125
        },
        {
            "unicode1": 87,
            "unicode2": 99,
            "advance": -0.02001953125
        },
        {
            "unicode1": 87,
            "unicode2": 100,
            "advance": -0.02001953125
        },
        {
            "unicode1": 87,
            "unicode2": 101,
            "advance": -0.02001953125
        },
        {
            "unicode1": 87,
            "unicode2": 103,
            "advance": -0.009765625
        },
        {
            "unicode1": 87,
            "unicode2": 109,
            "advance": -0.009765625
        },
        {
            "unicode1": 87,
            "unicode2": 110,
            "advance": -0.009765625
        },
        {
            "unicode1": 87,
            "unicode2": 111,
            "advance": -0.02001953125
        },
        {
            "unicode1": 87,
            "unicode2": 112,
            "advance": -0.009765625
        },
        {
            "unicode1": 87,
            "unicode2": 113,
            "advance": -0.02001953125
        },
        {
            "unicode1": 87,
            "unicode2": 114,
            "advance": -0.009765625
        },
        {
            "unicode1": 87,
            "unicode2": 115,
            "advance": -0.009765625
        },
        {
            "unicode1": 87,
            "unicode2": 117,
            "advance": -0.009765625
        },
        {
            "unicode1": 88,
            "unicode2": 67,
            "advance": -0.02001953125
        },
        {
            "unicode1": 88,
            "unicode2": 71,
            "advance": -0.02001953125
        },
        {
            "unicode1": 88,
            "unicode2": 79,
            "advance": -0.02001953125
        },
        {
            "unicode1": 88,
            "unicode2": 81,
            "advance": -0.02001953125
        },
        {
            "unicode1": 89,
            "unicode2": 44,
            "advance": -0.06005859375
        },
        {
            "unicode1": 89,
            "unicode2": 46,
            "advance": -0.06005859375
        },
        {
            "unicode1": 89,
            "unicode2": 63,
            "advance": 0.02001953125
        },
        {
            "unicode1": 89,
            "unicode2": 65,
            "advance": -0.06005859375
        },
        {
            "unicode1": 89,
            "unicode2": 67,
            "advance": -0.02001953125
        },
        {
            "unicode1": 89,
            "unicode2": 71,
            "advance": -0.02001953125
        },
        {
            "unicode1": 89,
            "unicode2": 79,
            "advance": -0.02001953125
        },
        {
            "unicode1": 89,
            "unicode2": 81,
            "advance": -0.02001953125
        },
        {
            "unicode1": 89,
            "unicode2": 97,
            "advance": -0.0498046875
        },
        {
            "unicode1": 89,
            "unicode2": 99,
            "advance": -0.0498046875
        },
        {
            "unicode1": 89,
            "unicode2": 100,
            "advance": -0.0498046875
        },
        {
            "unicode1": 89,
            "unicode2": 101,
            "advance": -0.0498046875
        },
        {
            "unicode1": 89,
            "unicode2": 103,
            "advance": -0.02001953125
        },
        {
            "unicode1": 89,
            "unicode2": 109,
            "advance": -0.02978515625
        },
        {
            "unicode1": 89,
            "unicode2": 110,
            "advance": -0.02978515625
        },
        {
            "unicode1": 89,
            "unicode2": 111,
            "advance": -0.0498046875
        },
        {
            "unicode1": 89,
            "unicode2": 112,
            "advance": -0.02978515625
        },
        {
            "unicode1": 89,
            "unicode2": 113,
            "advance": -0.0498046875
        },
        {
            "unicode1": 89,
            "unicode2": 114,
            "advance": -0.02978515625
        },
        {
            "unicode1": 89,
            "unicode2": 115,
            "advance": -0.0400390625
        },
        {
            "unicode1": 89,
            "unicode2": 117,
            "advance": -0.02978515625
        },
        {
            "unicode1": 89,
            "unicode2": 122,
            "advance": -0.02001953125
        },
        {
            "unicode1": 90,
            "unicode2": 67,
            "advance": -0.009765625
        },
        {
            "unicode1": 90,
            "unicode2": 71,
            "advance": -0.009765625
        },
        {
            "unicode1": 90,
            "unicode2": 79,
            "advance": -0.009765625
        },
        {
            "unicode1": 90,
            "unicode2": 81,
            "advance": -0.009765625
        },
        {
            "unicode1": 91,
            "unicode2": 74,
            "advance": 0.08984375
        },
        {
            "unicode1": 97,
            "unicode2": 34,
            "advance": -0.009765625
        },
        {
            "unicode1": 97,
            "unicode2": 39,
            "advance": -0.009765625
        },
        {
            "unicode1": 98,
            "unicode2": 34,
            "advance": -0.009765625
        },
        {
            "unicode1": 98,
            "unicode2": 39,
            "advance": -0.009765625
        },
        {
            "unicode1": 98,
            "unicode2": 118,
            "advance": -0.02001953125
        },
        {
            "unicode1": 98,
            "unicode2": 119,
            "advance": -0.02001953125
        },
        {
            "unicode1": 98,
            "unicode2": 120,
            "advance": -0.02001953125
        },
        {
            "unicode1": 98,
            "unicode2": 121,
            "advance": -0.02001953125
        },
        {
            "unicode1": 98,
            "unicode2": 122,
            "advance": -0.009765625
        },
        {
            "unicode1": 99,
            "unicode2": 34,
            "advance": 0.02001953125
        },
        {
            "unicode1": 99,
            "unicode2": 39,
            "advance": 0.02001953125
        },
        {
            "unicode1": 101,
            "unicode2": 34,
            "advance": -0.009765625
        },
        {
            "unicode1": 101,
            "unicode2": 39,
            "advance": -0.009765625
        },
        {
            "unicode1": 101,
            "unicode2": 118,
            "advance": -0.02001953125
        },
        {
            "unicode1": 101,
            "unicode2": 119,
            "advance": -0.02001953125
        },
        {
            "unicode1": 101,
            "unicode2": 120,
            "advance": -0.02001953125
        },
        {
            "unicode1": 101,
            "unicode2": 121,
            "advance": -0.02001953125
        },
        {
            "unicode1": 101,
            "unicode2": 122,
            "advance": -0.009765625
        },
        {
            "unicode1": 102,
            "unicode2": 34,
            "advance": 0.06005859375
        },
        {
            "unicode1": 102,
            "unicode2": 39,
            "advance": 0.06005859375
        },
        {
            "unicode1": 104,
            "unicode2": 34,
            "advance": -0.009765625
        },
        {
            "unicode1": 104,
            "unicode2": 39,
            "advance": -0.009765625
        },
        {
            "unicode1": 107,
            "unicode2": 99,
            "advance": -0.02001953125
        },
        {
            "unicode1": 107,
            "unicode2": 100,
            "advance": -0.02001953125
        },
        {
            "unicode1": 107,
            "unicode2": 101,
            "advance": -0.02001953125
        },
        {
            "unicode1": 107,
            "unicode2": 111,
            "advance": -0.02001953125
        },
        {
            "unicode1": 107,
            "unicode2": 113,
            "advance": -0.02001953125
        },
        {
            "unicode1": 109,
            "unicode2": 34,
            "advance": -0.009765625
        },
        {
            "unicode1": 109,
            "unicode2": 39,
            "advance": -0.009765625
        },
        {
            "unicode1": 110,
            "unicode2": 34,
            "advance": -0.009765625
        },
        {
            "unicode1": 110,
            "unicode2": 39,
            "advance": -0.009765625
        },
        {
            "unicode1": 111,
            "unicode2": 34,
            "advance": -0.009765625
        },
        {
            "unicode1": 111,
            "unicode2": 39,
            "advance": -0.009765625
        },
        {
            "unicode1": 111,
            "unicode2": 118,
            "advance": -0.02001953125
        },
        {
            "unicode1": 111,
            "unicode2": 119,
            "advance": -0.02001953125
        },
        {
            "unicode1": 111,
            "unicode2": 120,
            "advance": -0.02001953125
        },
        {
            "unicode1": 111,
            "unicode2": 121,
            "advance": -0.02001953125
        },
        {
            "unicode1": 111,
            "unicode2": 122,
            "advance": -0.009765625
        },
        {
            "unicode1": 112,
            "unicode2": 34,
            "advance": -0.009765625
        },
        {
            "unicode1": 112,
            "unicode2": 39,
            "advance": -0.009765625
        },
        {
            "unicode1": 112,
            "unicode2": 118,
            "advance": -0.02001953125
        },
        {
            "unicode1": 112,
            "unicode2": 119,
            "advance": -0.02001953125
        },
        {
            "unicode1": 112,
            "unicode2": 120,
            "advance": -0.02001953125
        },
        {
            "unicode1": 112,
            "unicode2": 121,
            "advance": -0.02001953125
        },
        {
            "unicode1": 112,
            "unicode2": 122,
            "advance": -0.009765625
        },
        {
            "unicode1": 114,
            "unicode2": 34,
            "advance": 0.0400390625
        },
        {
            "unicode1": 114,
            "unicode2": 39,
            "advance": 0.0400390625
        },
        {
            "unicode1": 114,
            "unicode2": 97,
            "advance": -0.02001953125
        },
        {
            "unicode1": 114,
            "unicode2": 99,
            "advance": -0.02001953125
        },
        {
            "unicode1": 114,
            "unicode2": 100,
            "advance": -0.02001953125
        },
        {
            "unicode1": 114,
            "unicode2": 101,
            "advance": -0.02001953125
        },
        {
            "unicode1": 114,
            "unicode2": 103,
            "advance": -0.009765625
        },
        {
            "unicode1": 114,
            "unicode2": 111,
            "advance": -0.02001953125
        },
        {
            "unicode1": 114,
            "unicode2": 113,
            "advance": -0.02001953125
        },
        {
            "unicode1": 116,
            "unicode2": 34,
            "advance": 0.02001953125
        },
        {
            "unicode1": 116,
            "unicode2": 39,
            "advance": 0.02001953125
        },
        {
            "unicode1": 118,
            "unicode2": 34,
            "advance": 0.0400390625
        },
        {
            "unicode1": 118,
            "unicode2": 39,
            "advance": 0.0400390625
        },
        {
            "unicode1": 118,
            "unicode2": 44,
            "advance": -0.0400390625
        },
        {
            "unicode1": 118,
            "unicode2": 46,
            "advance": -0.0400390625
        },
        {
            "unicode1": 118,
            "unicode2": 63,
            "advance": 0.02001953125
        },
        {
            "unicode1": 119,
            "unicode2": 34,
            "advance": 0.0400390625
        },
        {
            "unicode1": 119,
            "unicode2": 39,
            "advance": 0.0400390625
        },
        {
            "unicode1": 119,
            "unicode2": 44,
            "advance": -0.0400390625
        },
        {
            "unicode1": 119,
            "unicode2": 46,
            "advance": -0.0400390625
        },
        {
            "unicode1": 119,
            "unicode2": 63,
            "advance": 0.02001953125
        },
        {
            "unicode1": 120,
            "unicode2": 99,
            "advance": -0.02001953125
        },
        {
            "unicode1": 120,
            "unicode2": 100,
            "advance": -0.02001953125
        },
        {
            "unicode1": 120,
            "unicode2": 101,
            "advance": -0.02001953125
        },
        {
            "unicode1": 120,
            "unicode2": 111,
            "advance": -0.02001953125
        },
        {
            "unicode1": 120,
            "unicode2": 113,
            "advance": -0.02001953125
        },
        {
            "unicode1": 121,
            "unicode2": 34,
            "advance": 0.0400390625
        },
        {
            "unicode1": 121,
            "unicode2": 39,
            "advance": 0.0400390625
        },
        {
            "unicode1": 121,
            "unicode2": 44,
            "advance": -0.0400390625
        },
        {
            "unicode1": 121,
            "unicode2": 46,
            "advance": -0.0400390625
        },
        {
            "unicode1": 121,
            "unicode2": 63,
            "advance": 0.02001953125
        },
        {
            "unicode1": 123,
            "unicode2": 74,
            "advance": 0.08984375
        }
    ]
}